README.txt
setup.cfg
setup.py
infrae/__init__.py
infrae.buildout.egg-info/PKG-INFO
infrae.buildout.egg-info/SOURCES.txt
infrae.buildout.egg-info/dependency_links.txt
infrae.buildout.egg-info/entry_points.txt
infrae.buildout.egg-info/namespace_packages.txt
infrae.buildout.egg-info/requires.txt
infrae.buildout.egg-info/top_level.txt
infrae.buildout.egg-info/zip-safe
infrae/buildout/__init__.py
