Metadata-Version: 1.0
Name: infrae.buildout
Version: 0.1dev-r27686
Summary: Buildout recipe to install a buildout
Home-page: https://svn.infrae.com/buildout/infrae.buildout
Author: Sylvain Viollon
Author-email: info@infrae.com
License: ZPL 2.1
Keywords: buildout recipe
Platform: UNKNOWN
Classifier: Framework :: Buildout
Classifier: License :: OSI Approved :: Zope Public License
